{"name": "254a23601823ba74743de92d25d02f8af6503928ed4045088bf7c5299cf683c8.packed", "size": 512016, "hashes": {"md5": "1dd0e0d64042fce0c37fabf1fbcaa85f", "sha1": "577108f2af13fba69aa53ff8c1911b85a06f5eed", "sha256": "54412f3f830f1ed778a855dcf7eaa960c06cd26a180cad61e46c292a2a90abba"}, "macho": {"cputype": "X86_64", "subtype": "X86_ALL, X86_64_ALL, I386_ALL, or 386", "filetype": "EXECUTE", "nlcs": 5, "slcs": 496, "flags": ["NOUNDEFS", "WEAK_DEFINES", "BINDS_TO_WEAK", "PIE"], "lcs": [{"cmd": "SEGMENT_64", "size": 72, "name": "__PAGEZERO", "vmaddr": 0, "vmsize": 4294967296, "offset": 0, "segsize": 0, "maxprot": "---", "initprot": "---", "nsects": 0, "entropy": 0, "sects": [], "flags": []}, {"cmd": "SEGMENT_64", "size": 152, "name": "__TEXT", "vmaddr": 4294967296, "vmsize": 512000, "offset": 0, "segsize": 512000, "maxprot": "rwx", "initprot": "r-x", "nsects": 1, "entropy": 0.9886873501470107, "sects": [{"name": "upxTEXT", "segname": "__TEXT", "addr": 4294968240, "offset": 944, "align": 3, "reloff": 0, "nreloc": 0, "size": 511056, "type": "REGULAR", "attrs": ["PURE_INSTRUCTIONS", "SOME_INSTRUCTIONS"]}], "flags": []}, {"cmd": "SEGMENT_64", "size": 72, "name": "__LINKEDIT", "vmaddr": 4295479296, "vmsize": 4096, "offset": 512000, "segsize": 16, "maxprot": "rwx", "initprot": "r--", "nsects": 0, "entropy": 0.0, "sects": [], "flags": []}, {"cmd": "VERSION_MIN_MACOSX", "cmd_size": 16, "version": "10.7.0", "sdk": "10.11.0"}, {"cmd": "UNIXTHREAD", "cmd_size": 184, "state": "x86_THREAD_STATE64", "count": 42}]}, "filepath": "/tmp/benign_json/254a23601823ba74743de92d25d02f8af6503928ed4045088bf7c5299cf683c8.packed", "entropy": 7.909437142117223}