{"name": "9c83eaa44219950d236da38b5385e2acf45beba703742cf2b34d8c60b3e9a283.packed", "size": 24592, "hashes": {"md5": "2acaad135513c6943231e505d7589238", "sha1": "5252109b69eb681f7aa31c3b6bd0bb0089eea44b", "sha256": "6598661e1295c0e1e739fb075252b33fe769fc911acd73f369f8e648a5f67588"}, "macho": {"cputype": "X86_64", "subtype": "X86_ALL, X86_64_ALL, I386_ALL, or 386", "filetype": "EXECUTE", "nlcs": 6, "slcs": 512, "flags": ["NOUNDEFS", "PIE"], "lcs": [{"cmd": "SEGMENT_64", "size": 72, "name": "__PAGEZERO", "vmaddr": 0, "vmsize": 4294967296, "offset": 0, "segsize": 0, "maxprot": "---", "initprot": "---", "nsects": 0, "entropy": 0, "sects": [], "flags": []}, {"cmd": "SEGMENT_64", "size": 152, "name": "__TEXT", "vmaddr": 4294967296, "vmsize": 24576, "offset": 0, "segsize": 24576, "maxprot": "rwx", "initprot": "r-x", "nsects": 1, "entropy": 0.9266662166249962, "sects": [{"name": "upxTEXT", "segname": "__TEXT", "addr": 4294968240, "offset": 944, "align": 3, "reloff": 0, "nreloc": 0, "size": 23632, "type": "REGULAR", "attrs": ["PURE_INSTRUCTIONS", "SOME_INSTRUCTIONS"]}], "flags": []}, {"cmd": "SEGMENT_64", "size": 72, "name": "__LINKEDIT", "vmaddr": 4294991872, "vmsize": 4096, "offset": 24576, "segsize": 16, "maxprot": "rwx", "initprot": "r--", "nsects": 0, "entropy": 0.0, "sects": [], "flags": []}, {"cmd": "VERSION_MIN_MACOSX", "cmd_size": 16, "version": "10.8.0", "sdk": "10.14.0"}, {"cmd": "SOURCE_VERSION", "cmd_size": 16, "version": "0.0.0.0.0"}, {"cmd": "UNIXTHREAD", "cmd_size": 184, "state": "x86_THREAD_STATE64", "count": 42}]}, "filepath": "/tmp/benign_json/9c83eaa44219950d236da38b5385e2acf45beba703742cf2b34d8c60b3e9a283.packed", "entropy": 7.410482787979682}