{"name": "db6bef93aeffa9ea6bd15b4c0481cfd70457eb74d6e6660cbb754d1be2916988.packed", "size": 40976, "hashes": {"md5": "f93746dfdb50bbd8609fb67ae2bbaa32", "sha1": "0c86950ddfa1195777333e8ddd8f0d679f4b8cf0", "sha256": "2a38a5817592ee93ebbc8bf60775104d8a2efc350d47fc13900a35582422ae10"}, "macho": {"cputype": "X86_64", "subtype": "X86_ALL, X86_64_ALL, I386_ALL, or 386", "filetype": "EXECUTE", "nlcs": 6, "slcs": 512, "flags": ["NOUNDEFS", "PIE"], "lcs": [{"cmd": "SEGMENT_64", "size": 72, "name": "__PAGEZERO", "vmaddr": 0, "vmsize": 4294967296, "offset": 0, "segsize": 0, "maxprot": "---", "initprot": "---", "nsects": 0, "entropy": 0, "sects": [], "flags": []}, {"cmd": "SEGMENT_64", "size": 152, "name": "__TEXT", "vmaddr": 4294967296, "vmsize": 40960, "offset": 0, "segsize": 40960, "maxprot": "rwx", "initprot": "r-x", "nsects": 1, "entropy": 0.9574089463881227, "sects": [{"name": "upxTEXT", "segname": "__TEXT", "addr": 4294968240, "offset": 944, "align": 3, "reloff": 0, "nreloc": 0, "size": 40016, "type": "REGULAR", "attrs": ["PURE_INSTRUCTIONS", "SOME_INSTRUCTIONS"]}], "flags": []}, {"cmd": "SEGMENT_64", "size": 72, "name": "__LINKEDIT", "vmaddr": 4295008256, "vmsize": 4096, "offset": 40960, "segsize": 16, "maxprot": "rwx", "initprot": "r--", "nsects": 0, "entropy": 0.0, "sects": [], "flags": []}, {"cmd": "VERSION_MIN_MACOSX", "cmd_size": 16, "version": "10.12.0", "sdk": "10.14.0"}, {"cmd": "SOURCE_VERSION", "cmd_size": 16, "version": "0.0.0.0.0"}, {"cmd": "UNIXTHREAD", "cmd_size": 184, "state": "x86_THREAD_STATE64", "count": 42}]}, "filepath": "/tmp/benign_json/db6bef93aeffa9ea6bd15b4c0481cfd70457eb74d6e6660cbb754d1be2916988.packed", "entropy": 7.657709960961747}